silhouetteRank/__init__.py
silhouetteRank/combine.py
silhouetteRank/combine_fast.py
silhouetteRank/do_gpd.R
silhouetteRank/do_kmeans.R
silhouetteRank/evaluate_2b.py
silhouetteRank/evaluate_exact_2b.py
silhouetteRank/evaluate_exact_continue.py
silhouetteRank/evaluate_exact_one_2b.py
silhouetteRank/evaluate_fast_2b.py
silhouetteRank/evaluate_fast_one_2b.py
silhouetteRank/prep.py
silhouetteRank/prep_fast.py
silhouetteRank/qval.R
silhouetteRank/silhouette_rank_one.py
silhouetteRank/silhouette_rank_wrapper.py
silhouetteRank/spatial_genes.py
silhouetteRank/use_previous_cluster.py
silhouetteRank-1.0.5.13.dist-info/METADATA
silhouetteRank-1.0.5.13.dist-info/WHEEL
silhouetteRank-1.0.5.13.dist-info/entry_points.txt
silhouetteRank-1.0.5.13.dist-info/top_level.txt
silhouetteRank-1.0.5.13.dist-info/RECORD
